gpuq/C.cpython-310-x86_64-linux-gnu.so
gpuq/C.pyi
gpuq/__init__.py
gpuq/_dist_info.py
gpuq/cuda.py
gpuq/datatypes.py
gpuq/hip.py
gpuq/impl.py
gpuq/py.typed
gpuq/short_names.py
gpuq/utils.py
gpuq/version.py
gpuq/csrc/types.h
gpuq-1.5.4.dist-info/METADATA
gpuq-1.5.4.dist-info/WHEEL
gpuq-1.5.4.dist-info/top_level.txt
gpuq-1.5.4.dist-info/RECORD
gpuq-1.5.4.dist-info/licenses/LICENSE
