Metadata-Version: 2.4
Name: gpuq
Version: 1.5.4
Summary: A multi-vendor GPU querying utility with minimal dependencies
Home-page: https://github.com/makodevai/gpuq
Download-URL: https://github.com/makodevai/gpuq
Author: Mako
Author-email: support@mako.dev
Requires-Python: >=3.10.0
License-File: LICENSE
Provides-Extra: dev
Requires-Dist: GitPython; extra == "dev"
Requires-Dist: mypy; extra == "dev"
Requires-Dist: black; extra == "dev"
Requires-Dist: pytest; extra == "dev"
Dynamic: author
Dynamic: author-email
Dynamic: description
Dynamic: description-content-type
Dynamic: download-url
Dynamic: home-page
Dynamic: license-file
Dynamic: provides-extra
Dynamic: requires-python
Dynamic: summary
